orgstackcli/__init__.py
orgstackcli/driver.py
orgstackcli/orgstack.py
orgstackcli/config/__init__.py
orgstackcli/config/settings.py
orgstackcli/utils/__init__.py
orgstackcli/utils/api_utils.py
orgstackcli/utils/arg_parser_utils.py
orgstackcli/utils/credentials_utils.py
orgstackcli/utils/env_utils.py
orgstackcli/utils/file_utils.py
orgstackcli/utils/http_utils.py
orgstackcli/utils/shell_utils.py
orgstackcli-0.1.6.dist-info/LICENSE.txt
orgstackcli-0.1.6.dist-info/METADATA
orgstackcli-0.1.6.dist-info/WHEEL
orgstackcli-0.1.6.dist-info/entry_points.txt
orgstackcli-0.1.6.dist-info/top_level.txt
orgstackcli-0.1.6.dist-info/RECORD
