Metadata-Version: 2.1
Name: orgstackcli
Version: 0.1.6
Summary: Command-line interface for the OrgStack platform
Home-page: https://pypi.org/project/orgstackcli/
Author: Christian Hogan
Author-email: christian@orgstack.io
License: Apache License 2.0
Platform: UNKNOWN
Classifier: Intended Audience :: Developers
Classifier: Natural Language :: English
Classifier: License :: OSI Approved :: Apache Software License
Classifier: Programming Language :: Python
Classifier: Programming Language :: Python :: 3
Requires-Dist: requests (==2.23.0)
